test/verilog.v
`timescale 1ns / 1ps

module cla_pg_unit(A, B, P, G); 
    input A, B; 
    output P, G;

xor G_XOR(P, A, B);
and G_AND(G, A, B);

endmodule

module carry_lookahead_unit_5bit(P, G, C_in, C); 
    input [4:0] P; 
    input [4:0] G; 
    input C_in; 
    output [4:0] C;

    wire t1, t2_a, t2_b, t3_a, t3_b, t3_c, t3_d;
    wire t4_a, t4_b, t4_c, t4_d;
    wire t5_a, t5_b, t5_c, t5_d, t5_e;

and G_C1_A(t1, P[0], C_in);
or  G_C1(C[0], G[0], t1);

and G_C2_A(t2_a, P[1], G[0]);
and G_C2_B(t2_b, P[1], P[0], C_in);
or  G_C2(C[1], G[1], t2_a, t2_b);

and G_C3_A(t3_a, P[2], G[1]);
and G_C3_B(t3_b, P[2], P[1], G[0]);
and G_C3_C(t3_c, P[2], P[1], P[0], C_in);
or  G_C3(C[2], G[2], t3_a, t3_b, t3_c);

and G_C4_A(t4_a, P[3], G[2]);
and G_C4_B(t4_b, P[3], P[2], G[1]);
and G_C4_C(t4_c, P[3], P[2], P[1], G[0]);
and G_C4_D(t4_d, P[3], P[2], P[1], P[0], C_in);
or  G_C4(C[3], G[3], t4_a, t4_b, t4_c, t4_d);

and G_C5_A(t5_a, P[4], G[3]);
and G_C5_B(t5_b, P[4], P[3], G[2]);
and G_C5_C(t5_c, P[4], P[3], P[2], G[1]);
and G_C5_D(t5_d, P[4], P[3], P[2], P[1],G[0]);
and G_C5_E(t5_e, P[4], P[3], P[2], P[1], P[0], C_in);
or  G_C5(C[4], G[4], t5_a, t5_b, t5_c, t5_d, t5_e);

endmodule

module cla_5bit(A, B, C_in, Sum, C_out); 
    input [4:0] A; 
    input [4:0] B; 
    input C_in; 
    output [4:0] Sum; 
    output C_out;

    wire [4:0] P;
    wire [4:0] G;
    wire [4:0] C;

cla_pg_unit PGU0 (
    .A(A[0]), .B(B[0]), .P(P[0]), .G(G[0])
);
cla_pg_unit PGU1 (
    .A(A[1]), .B(B[1]), .P(P[1]), .G(G[1])
);
cla_pg_unit PGU2 (
    .A(A[2]), .B(B[2]), .P(P[2]), .G(G[2])
);
cla_pg_unit PGU3 (
    .A(A[3]), .B(B[3]), .P(P[3]), .G(G[3])
);
cla_pg_unit PGU4 (
    .A(A[4]), .B(B[4]), .P(P[4]), .G(G[4])
);


carry_lookahead_unit_5bit CLU (
    .P(P),
    .G(G),
    .C_in(C_in),
    .C({C_out, C[3], C[2], C[1], C[0]})
);

xor G_SUM0(Sum[0], P[0], C_in);
xor G_SUM1(Sum[1], P[1], C[0]);
xor G_SUM2(Sum[2], P[2], C[1]);
xor G_SUM3(Sum[3], P[3], C[2]);
xor G_SUM4(Sum[4], P[4], C[3]);

endmodule

test/verilog_tb.v
`timescale 1ns / 1ps

////////////////////////////////////////////////////////////////////////////////
//
// Exhaustive Testbench for 5-bit Carry Lookahead Adder (cla_5bit)
//
// This testbench iterates through all 2048 possible input combinations
// (2^5 for A * 2^5 for B * 2^1 for C_in) to fully verify the adder's
// functionality.
//
////////////////////////////////////////////////////////////////////////////////

module cla_5bit_tb;

    // Inputs to the UUT (Unit Under Test) are declared as 'reg'
    reg [4:0] A_tb;
    reg [4:0] B_tb;
    reg C_in_tb;

    // Outputs from the UUT are declared as 'wire'
    wire [4:0] Sum_tb;
    wire C_out_tb;

    // Instantiation of the Unit Under Test (UUT)
    // This connects our testbench regs/wires to the adder module
    cla_5bit uut (
        .A(A_tb),
        .B(B_tb),
        .C_in(C_in_tb),
        .Sum(Sum_tb),
        .C_out(C_out_tb)
    );

    // --- Verification Logic ---
    
    // Create a 6-bit "expected" value.
    // Verilog's built-in '+' operator is a perfect reference model for addition.
    wire [5:0] expected_result = A_tb + B_tb + C_in_tb;
    
    // Create a 6-bit "actual" value by combining the adder's outputs
    wire [5:0] actual_result = {C_out_tb, Sum_tb};

    // Test sequence
    integer i, j, k; // Loop counters
    integer error_count = 0; // Error counter

    initial begin
        // --- Setup ---
        // Setup waveform dumping (VCD)
        $dumpfile("cla_5bit.vcd");
        $dumpvars(0, cla_5bit_tb);

        // Setup a monitor to print changes. %d displays values as decimals.
        $monitor("Time=%t | A=%d B=%d Cin=%b | Cout=%b Sum=%b (Actual=%d, Expected=%d)",
                 $time, A_tb, B_tb, C_in_tb, C_out_tb, Sum_tb, actual_result, expected_result);

        // Initialize all inputs to 0
        A_tb = 5'd0;
        B_tb = 5'd0;
        C_in_tb = 1'b0;
        error_count = 0;
        
        #20; // Wait 20ns for initial propagation

        // --- Test Execution ---
        
        // Loop through all 2 possibilities for C_in (0 to 1)
        for (k = 0; k < 2; k = k + 1) begin
            C_in_tb = k;
            
            // Loop through all 2^5=32 possibilities for A (0 to 31)
            for (i = 0; i < 32; i = i + 1) begin
                A_tb = i;
                
                // Loop through all 2^5=32 possibilities for B (0 to 31)
                for (j = 0; j < 32; j = j + 1) begin
                    B_tb = j;
                    
                    #10; // Wait 10ns for the adder logic to settle
                    
                    // --- Check ---
                    // Compare the actual result with the expected result
                    if (actual_result !== expected_result) begin
                        $display("ERROR! A=%d B=%d Cin=%b | Actual=%b Expected=%b",
                                 A_tb, B_tb, C_in_tb, actual_result, expected_result);
                        error_count = error_count + 1;
                    end
                end
            end
        end

        #20; // Wait a little longer at the end

        // --- Reporting ---
        if (error_count == 0) begin
            $display("***************************************************");
            $display("SUCCESS: All %d test cases passed!", 2048);
            $display("***************************************************");
        end else begin
            $display("***************************************************");
            $display("FAILURE: %d errors found out of %d test cases.", error_count, 2048);
            $display("***************************************************");
        end
        
        $finish; // End the simulation
    end

endmodule

test/cla_5bit.vcd
$date
	Tue Nov 18 00:28:27 2025
$end
$version
	Icarus Verilog
$end
$timescale
	1ps
$end
$scope module cla_5bit_tb $end
$var wire 6 ! expected_result [5:0] $end
$var wire 6 " actual_result [5:0] $end
$var wire 5 # Sum_tb [4:0] $end
$var wire 1 $ C_out_tb $end
$var reg 5 % A_tb [4:0] $end
$var reg 5 & B_tb [4:0] $end
$var reg 1 ' C_in_tb $end
$var integer 32 ( error_count [31:0] $end
$var integer 32 ) i [31:0] $end
$var integer 32 * j [31:0] $end
$var integer 32 + k [31:0] $end
$scope module uut $end
$var wire 5 , A [4:0] $end
$var wire 5 - B [4:0] $end
$var wire 1 ' C_in $end
$var wire 5 . Sum [4:0] $end
$var wire 5 / P [4:0] $end
$var wire 5 0 G [4:0] $end
$var wire 1 $ C_out $end
$var wire 5 1 C [4:0] $end
$scope module CLU $end
$var wire 1 ' C_in $end
$var wire 5 2 G [4:0] $end
$var wire 5 3 P [4:0] $end
$var wire 1 4 t1 $end
$var wire 1 5 t2_a $end
$var wire 1 6 t2_b $end
$var wire 1 7 t3_a $end
$var wire 1 8 t3_b $end
$var wire 1 9 t3_c $end
$var wire 1 : t4_a $end
$var wire 1 ; t4_b $end
$var wire 1 < t4_c $end
$var wire 1 = t4_d $end
$var wire 1 > t5_a $end
$var wire 1 ? t5_b $end
$var wire 1 @ t5_c $end
$var wire 1 A t5_d $end
$var wire 1 B t5_e $end
$var wire 5 C C [4:0] $end
$upscope $end
$scope module PGU0 $end
$var wire 1 D A $end
$var wire 1 E B $end
$var wire 1 F G $end
$var wire 1 G P $end
$upscope $end
$scope module PGU1 $end
$var wire 1 H A $end
$var wire 1 I B $end
$var wire 1 J G $end
$var wire 1 K P $end
$upscope $end
$scope module PGU2 $end
$var wire 1 L A $end
$var wire 1 M B $end
$var wire 1 N G $end
$var wire 1 O P $end
$upscope $end
$scope module PGU3 $end
$var wire 1 P A $end
$var wire 1 Q B $end
$var wire 1 R G $end
$var wire 1 S P $end
$upscope $end
$scope module PGU4 $end
$var wire 1 T A $end
$var wire 1 U B $end
$var wire 1 V G $end
$var wire 1 W P $end
$upscope $end
$upscope $end
$upscope $end
$enddefinitions $end
$comment Show the parameter values. $end
$dumpall
$end
#0
$dumpvars
0W
0V
0U
0T
0S
0R
0Q
0P
0O
0N
0M
0L
0K
0J
0I
0H
0G
0F
0E
0D
b0 C
0B
0A
0@
0?
0>
0=
0<
0;
0:
09
08
07
06
05
04
b0 3
b0 2
bz0000 1
b0 0
b0 /
b0 .
b0 -
b0 ,
bx +
bx *
bx )
b0 (
0'
b0 &
b0 %
0$
b0 #
b0 "
b0 !
$end
#20000
b0 *
b0 )
b0 +
#30000
b1 "
b1 #
b1 .
b1 /
b1 3
1G
1E
b1 !
b1 &
b1 -
b1 *
#40000
b10 "
b10 #
b10 .
0G
b10 /
b10 3
1K
0E
1I
b10 !
b10 &
b10 -
b10 *
#50000
b11 "
b11 #
b11 .
b11 /
b11 3
1G
1E
b11 !
b11 &
b11 -
b11 *
#60000
b100 "
b100 #
b100 .
0G
0K
b100 /
b100 3
1O
0E
0I
1M
b100 !
b100 &
b100 -
b100 *
#70000
b101 "
b101 #
b101 .
b101 /
b101 3
1G
1E
b101 !
b101 &
b101 -
b101 *
#80000
b110 "
b110 #
b110 .
0G
b110 /
b110 3
1K
0E
1I
b110 !
b110 &
b110 -
b110 *
#90000
b111 "
b111 #
b111 .
b111 /
b111 3
1G
1E
b111 !
b111 &
b111 -
b111 *
#100000
b1000 "
b1000 #
b1000 .
0G
0K
0O
b1000 /
b1000 3
1S
0E
0I
0M
1Q
b1000 !
b1000 &
b1000 -
b1000 *
#110000
b1001 "
b1001 #
b1001 .
b1001 /
b1001 3
1G
1E
b1001 !
b1001 &
b1001 -
b1001 *
#120000
b1010 "
b1010 #
b1010 .
0G
b1010 /
b1010 3
1K
0E
1I
b1010 !
b1010 &
b1010 -
b1010 *
#130000
b1011 "
b1011 #
b1011 .
b1011 /
b1011 3
1G
1E
b1011 !
b1011 &
b1011 -
b1011 *
#140000
b1100 "
b1100 #
b1100 .
0G
0K
b1100 /
b1100 3
1O
0E
0I
1M
b1100 !
b1100 &
b1100 -
b1100 *
#150000
b1101 "
b1101 #
b1101 .
b1101 /
b1101 3
1G
1E
b1101 !
b1101 &
b1101 -
b1101 *
#160000
b1110 "
b1110 #
b1110 .
0G
b1110 /
b1110 3
1K
0E
1I
b1110 !
b1110 &
b1110 -
b1110 *
#170000
b1111 "
b1111 #
b1111 .
b1111 /
b1111 3
1G
1E
b1111 !
b1111 &
b1111 -
b1111 *
#180000
b10000 "
b10000 #
b10000 .
0G
0K
0O
0S
b10000 /
b10000 3
1W
0E
0I
0M
0Q
1U
b10000 !
b10000 &
b10000 -
b10000 *
#190000
b10001 "
b10001 #
b10001 .
b10001 /
b10001 3
1G
1E
b10001 !
b10001 &
b10001 -
b10001 *
#200000
b10010 "
b10010 #
b10010 .
0G
b10010 /
b10010 3
1K
0E
1I
b10010 !
b10010 &
b10010 -
b10010 *
#210000
b10011 "
b10011 #
b10011 .
b10011 /
b10011 3
1G
1E
b10011 !
b10011 &
b10011 -
b10011 *
#220000
b10100 "
b10100 #
b10100 .
0G
0K
b10100 /
b10100 3
1O
0E
0I
1M
b10100 !
b10100 &
b10100 -
b10100 *
#230000
b10101 "
b10101 #
b10101 .
b10101 /
b10101 3
1G
1E
b10101 !
b10101 &
b10101 -
b10101 *
#240000
b10110 "
b10110 #
b10110 .
0G
b10110 /
b10110 3
1K
0E
1I
b10110 !
b10110 &
b10110 -
b10110 *
#250000
b10111 "
b10111 #
b10111 .
b10111 /
b10111 3
1G
1E
b10111 !
b10111 &
b10111 -
b10111 *
#260000
b11000 "
b11000 #
b11000 .
0G
0K
0O
b11000 /
b11000 3
1S
0E
0I
0M
1Q
b11000 !
b11000 &
b11000 -
b11000 *
#270000
b11001 "
b11001 #
b11001 .
b11001 /
b11001 3
1G
1E
b11001 !
b11001 &
b11001 -
b11001 *
#280000
b11010 "
b11010 #
b11010 .
0G
b11010 /
b11010 3
1K
0E
1I
b11010 !
b11010 &
b11010 -
b11010 *
#290000
b11011 "
b11011 #
b11011 .
b11011 /
b11011 3
1G
1E
b11011 !
b11011 &
b11011 -
b11011 *
#300000
b11100 "
b11100 #
b11100 .
0G
0K
b11100 /
b11100 3
1O
0E
0I
1M
b11100 !
b11100 &
b11100 -
b11100 *
#310000
b11101 "
b11101 #
b11101 .
b11101 /
b11101 3
1G
1E
b11101 !
b11101 &
b11101 -
b11101 *
#320000
b11110 "
b11110 #
b11110 .
0G
b11110 /
b11110 3
1K
0E
1I
b11110 !
b11110 &
b11110 -
b11110 *
#330000
b11111 "
b11111 #
b11111 .
b11111 /
b11111 3
1G
1E
b11111 !
b11111 &
b11111 -
b11111 *
#340000
b1 "
b1 #
b1 .
0K
0O
0S
b1 /
b1 3
0W
0E
0I
0M
0Q
0U
1D
b0 &
b0 -
b1 !
b1 %
b1 ,
b1 )
b0 *
#350000
bz0001 1
b10 "
b10 #
b10 .
b1 C
b0 /
b0 3
0G
b1 0
b1 2
1F
1E
b10 !
b1 &
b1 -
b1 *
#360000
bz0000 1
b0 C
b11 "
b11 #
b11 .
1G
b0 0
b0 2
0F
b11 /
b11 3
1K
0E
1I
b11 !
b10 &
b10 -
b10 *
#370000
bz0011 1
b100 "
b100 #
b100 .
b11 C
15
b10 /
b10 3
0G
b1 0
b1 2
1F
1E
b100 !
b11 &
b11 -
b11 *
#380000
bz0000 1
b0 C
05
b101 "
b101 #
b101 .
1G
b0 0
b0 2
0F
0K
b101 /
b101 3
1O
0E
0I
1M
b101 !
b100 &
b100 -
b100 *
#390000
bz0001 1
b110 "
b110 #
b110 .
b1 C
b100 /
b100 3
0G
b1 0
b1 2
1F
1E
b110 !
b101 &
b101 -
b101 *
#400000
bz0000 1
b0 C
b111 "
b111 #
b111 .
1G
b0 0
b0 2
0F
b111 /
b111 3
1K
0E
1I
b111 !
b110 &
b110 -
b110 *
#410000
bz0111 1
b1000 "
b1000 #
b1000 .
b111 C
15
18
b110 /
b110 3
0G
b1 0
b1 2
1F
1E
b1000 !
b111 &
b111 -
b111 *
#420000
bz0000 1
b0 C
05
08
b1001 "
b1001 #
b1001 .
1G
b0 0
b0 2
0F
0K
0O
b1001 /
b1001 3
1S
0E
0I
0M
1Q
b1001 !
b1000 &
b1000 -
b1000 *
#430000
bz0001 1
b1010 "
b1010 #
b1010 .
b1 C
b1000 /
b1000 3
0G
b1 0
b1 2
1F
1E
b1010 !
b1001 &
b1001 -
b1001 *
#440000
bz0000 1
b0 C
b1011 "
b1011 #
b1011 .
1G
b0 0
b0 2
0F
b1011 /
b1011 3
1K
0E
1I
b1011 !
b1010 &
b1010 -
b1010 *
#450000
bz0011 1
b1100 "
b1100 #
b1100 .
b11 C
15
b1010 /
b1010 3
0G
b1 0
b1 2
1F
1E
b1100 !
b1011 &
b1011 -
b1011 *
#460000
bz0000 1
b0 C
05
b1101 "
b1101 #
b1101 .
1G
b0 0
b0 2
0F
0K
b1101 /
b1101 3
1O
0E
0I
1M
b1101 !
b1100 &
b1100 -
b1100 *
#470000
bz0001 1
b1110 "
b1110 #
b1110 .
b1 C
b1100 /
b1100 3
0G
b1 0
b1 2
1F
1E
b1110 !
b1101 &
b1101 -
b1101 *
#480000
bz0000 1
b0 C
b1111 "
b1111 #
b1111 .
1G
b0 0
b0 2
0F
b1111 /
b1111 3
1K
0E
1I
b1111 !
b1110 &
b1110 -
b1110 *
#490000
bz1111 1
b10000 "
b10000 #
b10000 .
b1111 C
15
18
1<
b1110 /
b1110 3
0G
b1 0
b1 2
1F
1E
b10000 !
b1111 &
b1111 -
b1111 *
#500000
bz0000 1
b0 C
05
08
0<
b10001 "
b10001 #
b10001 .
1G
b0 0
b0 2
0F
0K
0O
0S
b10001 /
b10001 3
1W
0E
0I
0M
0Q
1U
b10001 !
b10000 &
b10000 -
b10000 *
#510000
bz0001 1
b10010 "
b10010 #
b10010 .
b1 C
b10000 /
b10000 3
0G
b1 0
b1 2
1F
1E
b10010 !
b10001 &
b10001 -
b10001 *
#520000
bz0000 1
b0 C
b10011 "
b10011 #
b10011 .
1G
b0 0
b0 2
0F
b10011 /
b10011 3
1K
0E
1I
b10011 !
b10010 &
b10010 -
b10010 *
#530000
bz0011 1
b10100 "
b10100 #
b10100 .
b11 C
15
b10010 /
b10010 3
0G
b1 0
b1 2
1F
1E
b10100 !
b10011 &
b10011 -
b10011 *
#540000
bz0000 1
b0 C
05
b10101 "
b10101 #
b10101 .
1G
b0 0
b0 2
0F
0K
b10101 /
b10101 3
1O
0E
0I
1M
b10101 !
b10100 &
b10100 -
b10100 *
#550000
bz0001 1
b10110 "
b10110 #
b10110 .
b1 C
b10100 /
b10100 3
0G
b1 0
b1 2
1F
1E
b10110 !
b10101 &
b10101 -
b10101 *
#560000
bz0000 1
b0 C
b10111 "
b10111 #
b10111 .
1G
b0 0
b0 2
0F
b10111 /
b10111 3
1K
0E
1I
b10111 !
b10110 &
b10110 -
b10110 *
#570000
bz0111 1
b11000 "
b11000 #
b11000 .
b111 C
15
18
b10110 /
b10110 3
0G
b1 0
b1 2
1F
1E
b11000 !
b10111 &
b10111 -
b10111 *
#580000
bz0000 1
b0 C
05
08
b11001 "
b11001 #
b11001 .
1G
b0 0
b0 2
0F
0K
0O
b11001 /
b11001 3
1S
0E
0I
0M
1Q
b11001 !
b11000 &
b11000 -
b11000 *
#590000
bz0001 1
b11010 "
b11010 #
b11010 .
b1 C
b11000 /
b11000 3
0G
b1 0
b1 2
1F
1E
b11010 !
b11001 &
b11001 -
b11001 *
#600000
bz0000 1
b0 C
b11011 "
b11011 #
b11011 .
1G
b0 0
b0 2
0F
b11011 /
b11011 3
1K
0E
1I
b11011 !
b11010 &
b11010 -
b11010 *
#610000
bz0011 1
b11100 "
b11100 #
b11100 .
b11 C
15
b11010 /
b11010 3
0G
b1 0
b1 2
1F
1E
b11100 !
b11011 &
b11011 -
b11011 *
#620000
bz0000 1
b0 C
05
b11101 "
b11101 #
b11101 .
1G
b0 0
b0 2
0F
0K
b11101 /
b11101 3
1O
0E
0I
1M
b11101 !
b11100 &
b11100 -
b11100 *
#630000
bz0001 1
b11110 "
b11110 #
b11110 .
b1 C
b11100 /
b11100 3
0G
b1 0
b1 2
1F
1E
b11110 !
b11101 &
b11101 -
b11101 *
#640000
bz0000 1
b0 C
b11111 "
b11111 #
b11111 .
1G
b0 0
b0 2
0F
b11111 /
b11111 3
1K
0E
1I
b11111 !
b11110 &
b11110 -
b11110 *
#650000
1$
bz1111 1
1A
b100000 "
b0 #
b0 .
b11111 C
15
18
1<
b11110 /
b11110 3
0G
b1 0
b1 2
1F
1E
b100000 !
b11111 &
b11111 -
b11111 *
#660000
0$
bz0000 1
0A
b10 "
b10 #
b10 .
b0 C
05
08
0<
0O
0S
b10 /
b10 3
0W
b0 0
b0 2
0F
0E
0I
0M
0Q
0U
0D
1H
b0 &
b0 -
b10 !
b10 %
b10 ,
b10 )
b0 *
#670000
b11 "
b11 #
b11 .
b11 /
b11 3
1G
1E
b11 !
b1 &
b1 -
b1 *
#680000
bz0010 1
b100 "
b100 #
b100 .
b10 C
0G
b0 /
b0 3
0K
b10 0
b10 2
1J
0E
1I
b100 !
b10 &
b10 -
b10 *
#690000
b101 "
b101 #
b101 .
b1 /
b1 3
1G
1E
b101 !
b11 &
b11 -
b11 *
#700000
bz0000 1
b0 C
b110 "
b110 #
b110 .
0G
1K
b0 0
b0 2
0J
b110 /
b110 3
1O
0E
0I
1M
b110 !
b100 &
b100 -
b100 *
#710000
b111 "
b111 #
b111 .
b111 /
b111 3
1G
1E
b111 !
b101 &
b101 -
b101 *
#720000
bz0110 1
b1000 "
b1000 #
b1000 .
b110 C
17
0G
b100 /
b100 3
0K
b10 0
b10 2
1J
0E
1I
b1000 !
b110 &
b110 -
b110 *
#730000
b1001 "
b1001 #
b1001 .
b101 /
b101 3
1G
1E
b1001 !
b111 &
b111 -
b111 *
#740000
bz0000 1
b0 C
07
b1010 "
b1010 #
b1010 .
0G
1K
b0 0
b0 2
0J
0O
b1010 /
b1010 3
1S
0E
0I
0M
1Q
b1010 !
b1000 &
b1000 -
b1000 *
#750000
b1011 "
b1011 #
b1011 .
b1011 /
b1011 3
1G
1E
b1011 !
b1001 &
b1001 -
b1001 *
#760000
bz0010 1
b1100 "
b1100 #
b1100 .
b10 C
0G
b1000 /
b1000 3
0K
b10 0
b10 2
1J
0E
1I
b1100 !
b1010 &
b1010 -
b1010 *
#770000
b1101 "
b1101 #
b1101 .
b1001 /
b1001 3
1G
1E
b1101 !
b1011 &
b1011 -
b1011 *
#780000
bz0000 1
b0 C
b1110 "
b1110 #
b1110 .
0G
1K
b0 0
b0 2
0J
b1110 /
b1110 3
1O
0E
0I
1M
b1110 !
b1100 &
b1100 -
b1100 *
#790000
b1111 "
b1111 #
b1111 .
b1111 /
b1111 3
1G
1E
b1111 !
b1101 &
b1101 -
b1101 *
#800000
bz1110 1
b10000 "
b10000 #
b10000 .
b1110 C
17
1;
0G
b1100 /
b1100 3
0K
b10 0
b10 2
1J
0E
1I
b10000 !
b1110 &
b1110 -
b1110 *
#810000
b10001 "
b10001 #
b10001 .
b1101 /
b1101 3
1G
1E
b10001 !
b1111 &
b1111 -
b1111 *
#820000
bz0000 1
b0 C
07
0;
b10010 "
b10010 #
b10010 .
0G
1K
b0 0
b0 2
0J
0O
0S
b10010 /
b10010 3
1W
0E
0I
0M
0Q
1U
b10010 !
b10000 &
b10000 -
b10000 *
#830000
b10011 "
b10011 #
b10011 .
b10011 /
b10011 3
1G
1E
b10011 !
b10001 &
b10001 -
b10001 *
#840000
bz0010 1
b10100 "
b10100 #
b10100 .
b10 C
0G
b10000 /
b10000 3
0K
b10 0
b10 2
1J
0E
1I
b10100 !
b10010 &
b10010 -
b10010 *
#850000
b10101 "
b10101 #
b10101 .
b10001 /
b10001 3
1G
1E
b10101 !
b10011 &
b10011 -
b10011 *
#860000
bz0000 1
b0 C
b10110 "
b10110 #
b10110 .
0G
1K
b0 0
b0 2
0J
b10110 /
b10110 3
1O
0E
0I
1M
b10110 !
b10100 &
b10100 -
b10100 *
#870000
b10111 "
b10111 #
b10111 .
b10111 /
b10111 3
1G
1E
b10111 !
b10101 &
b10101 -
b10101 *
#880000
bz0110 1
b11000 "
b11000 #
b11000 .
b110 C
17
0G
b10100 /
b10100 3
0K
b10 0
b10 2
1J
0E
1I
b11000 !
b10110 &
b10110 -
b10110 *
#890000
b11001 "
b11001 #
b11001 .
b10101 /
b10101 3
1G
1E
b11001 !
b10111 &
b10111 -
b10111 *
#900000
bz0000 1
b0 C
07
b11010 "
b11010 #
b11010 .
0G
1K
b0 0
b0 2
0J
0O
b11010 /
b11010 3
1S
0E
0I
0M
1Q
b11010 !
b11000 &
b11000 -
b11000 *
#910000
b11011 "
b11011 #
b11011 .
b11011 /
b11011 3
1G
1E
b11011 !
b11001 &
b11001 -
b11001 *
#920000
bz0010 1
b11100 "
b11100 #
b11100 .
b10 C
0G
b11000 /
b11000 3
0K
b10 0
b10 2
1J
0E
1I
b11100 !
b11010 &
b11010 -
b11010 *
#930000
b11101 "
b11101 #
b11101 .
b11001 /
b11001 3
1G
1E
b11101 !
b11011 &
b11011 -
b11011 *
#940000
bz0000 1
b0 C
b11110 "
b11110 #
b11110 .
0G
1K
b0 0
b0 2
0J
b11110 /
b11110 3
1O
0E
0I
1M
b11110 !
b11100 &
b11100 -
b11100 *
#950000
b11111 "
b11111 #
b11111 .
b11111 /
b11111 3
1G
1E
b11111 !
b11101 &
b11101 -
b11101 *
#960000
1$
bz1110 1
b100000 "
b0 #
b0 .
b11110 C
17
1;
1@
0G
b11100 /
b11100 3
0K
b10 0
b10 2
1J
0E
1I
b100000 !
b11110 &
b11110 -
b11110 *
#970000
b100001 "
b1 #
b1 .
b11101 /
b11101 3
1G
1E
b100001 !
b11111 &
b11111 -
b11111 *
#980000
0$
bz0000 1
b0 C
07
0;
b11 "
b11 #
b11 .
0@
1K
b0 0
b0 2
0J
0O
0S
b11 /
b11 3
0W
0E
0I
0M
0Q
0U
1D
b0 &
b0 -
b11 !
b11 %
b11 ,
b11 )
b0 *
#990000
bz0011 1
b100 "
b100 #
b100 .
b11 C
15
b10 /
b10 3
0G
b1 0
b1 2
1F
1E
b100 !
b1 &
b1 -
b1 *
#1000000
bz0010 1
b10 C
b101 "
b101 #
b101 .
05
1G
0F
b1 /
b1 3
0K
b10 0
b10 2
1J
0E
1I
b101 !
b10 &
b10 -
b10 *
#1010000
bz0011 1
b110 "
b110 #
b110 .
b11 C
b0 /
b0 3
0G
b11 0
b11 2
1F
1E
b110 !
b11 &
b11 -
b11 *
#1020000
bz0000 1
b0 C
b111 "
b111 #
b111 .
1G
0F
1K
b0 0
b0 2
0J
b111 /
b111 3
1O
0E
0I
1M
b111 !
b100 &
b100 -
b100 *
#1030000
bz0111 1
b1000 "
b1000 #
b1000 .
b111 C
15
18
b110 /
b110 3
0G
b1 0
b1 2
1F
1E
b1000 !
b101 &
b101 -
b101 *
#1040000
bz0110 1
b110 C
b1001 "
b1001 #
b1001 .
05
08
17
1G
0F
b101 /
b101 3
0K
b10 0
b10 2
1J
0E
1I
b1001 !
b110 &
b110 -
b110 *
#1050000
bz0111 1
b1010 "
b1010 #
b1010 .
b111 C
b100 /
b100 3
0G
b11 0
b11 2
1F
1E
b1010 !
b111 &
b111 -
b111 *
#1060000
bz0000 1
b0 C
07
b1011 "
b1011 #
b1011 .
1G
0F
1K
b0 0
b0 2
0J
0O
b1011 /
b1011 3
1S
0E
0I
0M
1Q
b1011 !
b1000 &
b1000 -
b1000 *
#1070000
bz0011 1
b1100 "
b1100 #
b1100 .
b11 C
15
b1010 /
b1010 3
0G
b1 0
b1 2
1F
1E
b1100 !
b1001 &
b1001 -
b1001 *
#1080000
bz0010 1
b10 C
b1101 "
b1101 #
b1101 .
05
1G
0F
b1001 /
b1001 3
0K
b10 0
b10 2
1J
0E
1I
b1101 !
b1010 &
b1010 -
b1010 *
#1090000
bz0011 1
b1110 "
b1110 #
b1110 .
b11 C
b1000 /
b1000 3
0G
b11 0
b11 2
1F
1E
b1110 !
b1011 &
b1011 -
b1011 *
#1100000
bz0000 1
b0 C
b1111 "
b1111 #
b1111 .
1G
0F
1K
b0 0
b0 2
0J
b1111 /
b1111 3
1O
0E
0I
1M
b1111 !
b1100 &
b1100 -
b1100 *
#1110000
bz1111 1
b10000 "
b10000 #
b10000 .
b1111 C
15
18
1<
b1110 /
b1110 3
0G
b1 0
b1 2
1F
1E
b10000 !
b1101 &
b1101 -
b1101 *
#1120000
bz1110 1
b1110 C
b10001 "
b10001 #
b10001 .
05
08
0<
17
1;
1G
0F
b1101 /
b1101 3
0K
b10 0
b10 2
1J
0E
1I
b10001 !
b1110 &
b1110 -
b1110 *
#1130000
bz1111 1
b10010 "
b10010 #
b10010 .
b1111 C
b1100 /
b1100 3
0G
b11 0
b11 2
1F
1E
b10010 !
b1111 &
b1111 -
b1111 *
#1140000
bz0000 1
b0 C
07
0;
b10011 "
b10011 #
b10011 .
1G
0F
1K
b0 0
b0 2
0J
0O
0S
b10011 /
b10011 3
1W
0E
0I
0M
0Q
1U
b10011 !
b10000 &
b10000 -
b10000 *
#1150000
bz0011 1
b10100 "
b10100 #
b10100 .
b11 C
15
b10010 /
b10010 3
0G
b1 0
b1 2
1F
1E
b10100 !
b10001 &
b10001 -
b10001 *
#1160000
bz0010 1
b10 C
b10101 "
b10101 #
b10101 .
05
1G
0F
b10001 /
b10001 3
0K
b10 0
b10 2
1J
0E
1I
b10101 !
b10010 &
b10010 -
b10010 *
#1170000
bz0011 1
b10110 "
b10110 #
b10110 .
b11 C
b10000 /
b10000 3
0G
b11 0
b11 2
1F
1E
b10110 !
b10011 &
b10011 -
b10011 *
#1180000
bz0000 1
b0 C
b10111 "
b10111 #
b10111 .
1G
0F
1K
b0 0
b0 2
0J
b10111 /
b10111 3
1O
0E
0I
1M
b10111 !
b10100 &
b10100 -
b10100 *
#1190000
bz0111 1
b11000 "
b11000 #
b11000 .
b111 C
15
18
b10110 /
b10110 3
0G
b1 0
b1 2
1F
1E
b11000 !
b10101 &
b10101 -
b10101 *
#1200000
bz0110 1
b110 C
b11001 "
b11001 #
b11001 .
05
08
17
1G
0F
b10101 /
b10101 3
0K
b10 0
b10 2
1J
0E
1I
b11001 !
b10110 &
b10110 -
b10110 *
#1210000
bz0111 1
b11010 "
b11010 #
b11010 .
b111 C
b10100 /
b10100 3
0G
b11 0
b11 2
1F
1E
b11010 !
b10111 &
b10111 -
b10111 *
#1220000
bz0000 1
b0 C
07
b11011 "
b11011 #
b11011 .
1G
0F
1K
b0 0
b0 2
0J
0O
b11011 /
b11011 3
1S
0E
0I
0M
1Q
b11011 !
b11000 &
b11000 -
b11000 *
#1230000
bz0011 1
b11100 "
b11100 #
b11100 .
b11 C
15
b11010 /
b11010 3
0G
b1 0
b1 2
1F
1E
b11100 !
b11001 &
b11001 -
b11001 *
#1240000
bz0010 1
b10 C
b11101 "
b11101 #
b11101 .
05
1G
0F
b11001 /
b11001 3
0K
b10 0
b10 2
1J
0E
1I
b11101 !
b11010 &
b11010 -
b11010 *
#1250000
bz0011 1
b11110 "
b11110 #
b11110 .
b11 C
b11000 /
b11000 3
0G
b11 0
b11 2
1F
1E
b11110 !
b11011 &
b11011 -
b11011 *
#1260000
bz0000 1
b0 C
b11111 "
b11111 #
b11111 .
1G
0F
1K
b0 0
b0 2
0J
b11111 /
b11111 3
1O
0E
0I
1M
b11111 !
b11100 &
b11100 -
b11100 *
#1270000
1$
bz1111 1
1A
b100000 "
b0 #
b0 .
b11111 C
15
18
1<
b11110 /
b11110 3
0G
b1 0
b1 2
1F
1E
b100000 !
b11101 &
b11101 -
b11101 *
#1280000
bz1110 1
0A
b11110 C
b100001 "
b1 #
b1 .
05
08
0<
17
1;
1@
1G
0F
b11101 /
b11101 3
0K
b10 0
b10 2
1J
0E
1I
b100001 !
b11110 &
b11110 -
b11110 *
