2024112005/verilog/brent_kung_5bit.v
// ========================================
// D Flip-Flop
// ========================================
module dff (input clk, input d, output reg q);
    always @(posedge clk)
        q <= d;
endmodule


// ========================================
// Black Cell  (P,G) combine
// ========================================
module black_cell(
    input  p_kj, g_kj,
    input  p_ji, g_ji,
    output p_ki, g_ki
);
    assign p_ki = p_kj & p_ji;
    assign g_ki = g_kj | (p_kj & g_ji);
endmodule


// ========================================
// Gray Cell  (G only combine)
// ========================================
module gray_cell(
    input p_kj, g_kj,
    input g_ji,
    output g_ki
);
    assign g_ki = g_kj | (p_kj & g_ji);
endmodule



// ========================================
// 5-bit Brent–Kung Adder (NO Cin)
// ========================================
module brent_kung_5bit(
    input clk,
    input [4:0] a_in,
    input [4:0] b_in,
    output [4:0] sum_out,
    output cout_out
);

    // ----------------------------------------
    // Register inputs
    // ----------------------------------------
    wire [4:0] a, b;

    dff da0 (clk, a_in[0], a[0]);
    dff da1 (clk, a_in[1], a[1]);
    dff da2 (clk, a_in[2], a[2]);
    dff da3 (clk, a_in[3], a[3]);
    dff da4 (clk, a_in[4], a[4]);

    dff db0 (clk, b_in[0], b[0]);
    dff db1 (clk, b_in[1], b[1]);
    dff db2 (clk, b_in[2], b[2]);
    dff db3 (clk, b_in[3], b[3]);
    dff db4 (clk, b_in[4], b[4]);



    // ----------------------------------------
    // P, G generation
    // ----------------------------------------
    wire [4:0] P, G;
    assign P = a ^ b;
    assign G = a & b;


    // ----------------------------------------
    // Brent–Kung Prefix Network
    // (No Cin, so carry-in = 0)
    // ----------------------------------------

    // ---- Level 1 ----
    wire p11, g11;
    black_cell L1_10 (P[1], G[1], P[0], G[0], p11, g11);

    wire p31, g31;
    black_cell L1_32 (P[3], G[3], P[2], G[2], p31, g31);


    // ---- Level 2 ----
    wire p22, g22;
    black_cell L2_210 (P[2], G[2], p11, g11, p22, g22);

    wire p32, g32;
    black_cell L2_310 (p31, g31, p11, g11, p32, g32);


    // ---- Level 3 ----
    wire p43, g43;
    black_cell L3_40123 (P[4], G[4], p32, g32, p43, g43);


    // ----------------------------------------
    // Carry Outputs (C0 = 0)
    // ----------------------------------------
    wire C1 = G[0];
    wire C2 = g11;
    wire C3 = g22;
    wire C4 = g32;
    wire C5 = g43;


    // ----------------------------------------
    // Sum computation
    // ----------------------------------------
    wire [4:0] sum;
    assign sum[0] = P[0];
    assign sum[1] = P[1] ^ C1;
    assign sum[2] = P[2] ^ C2;
    assign sum[3] = P[3] ^ C3;
    assign sum[4] = P[4] ^ C4;

    // ----------------------------------------
    // Register outputs (explicit DFFs)
    // ----------------------------------------
    dff ds0 (.clk(clk), .d(sum[0]), .q(sum_out[0]));
    dff ds1 (.clk(clk), .d(sum[1]), .q(sum_out[1]));
    dff ds2 (.clk(clk), .d(sum[2]), .q(sum_out[2]));
    dff ds3 (.clk(clk), .d(sum[3]), .q(sum_out[3]));
    dff ds4 (.clk(clk), .d(sum[4]), .q(sum_out[4]));

    // DFF for final carry
    dff dcout (.clk(clk), .d(C5), .q(cout_out));

endmodule

verilog/tb_brent_kung_5bit.v
`timescale 1ns / 1ps

module tb_brent_kung_5bit;

    reg clk;
    reg [4:0] a_in;
    reg [4:0] b_in;

    wire [4:0] sum_out;
    wire cout_out;

    brent_kung_5bit uut (
        .clk(clk),
        .a_in(a_in),
        .b_in(b_in),
        .sum_out(sum_out),
        .cout_out(cout_out)
    );


    initial clk = 0;
    always #5 clk = ~clk;

    initial begin
        $dumpfile("brent_kung_5bit_tb.vcd");
        $dumpvars(0, tb_brent_kung_5bit);

        a_in = 5'b00001; b_in = 5'b00010; #20;

        a_in = 5'b00101; b_in = 5'b00011; #20;

        a_in = 5'b11111; b_in = 5'b00001; #20;

        a_in = 5'b10101; b_in = 5'b01010; #20;

        a_in = 5'b01111; b_in = 5'b00101; #20;

        $finish;
    end

    

   reg [4:0] a_d1, b_d1;
reg [4:0] a_d2, b_d2;

always @(posedge clk) begin
    a_d1 <= a_in;
    b_d1 <= b_in;
    a_d2 <= a_d1;
    b_d2 <= b_d1;
    $display("time=%0t | a=%b b=%b | sum=%b cout=%b",
             $time, a_d2, b_d2, sum_out, cout_out);
end



endmodule

verilog/brent_kung_5bit_tb.vcd
$date
	Mon Dec  1 20:01:13 2025
$end
$version
	Icarus Verilog
$end
$timescale
	1ps
$end
$scope module tb_brent_kung_5bit $end
$var wire 5 ! sum_out [4:0] $end
$var wire 1 " cout_out $end
$var reg 5 # a_d1 [4:0] $end
$var reg 5 $ a_d2 [4:0] $end
$var reg 5 % a_in [4:0] $end
$var reg 5 & b_d1 [4:0] $end
$var reg 5 ' b_d2 [4:0] $end
$var reg 5 ( b_in [4:0] $end
$var reg 1 ) clk $end
$scope module uut $end
$var wire 1 * C2 $end
$var wire 1 + C3 $end
$var wire 1 , C4 $end
$var wire 1 - C5 $end
$var wire 5 . G [4:0] $end
$var wire 5 / P [4:0] $end
$var wire 5 0 a_in [4:0] $end
$var wire 5 1 b_in [4:0] $end
$var wire 1 ) clk $end
$var wire 5 2 sum_out [4:0] $end
$var wire 5 3 sum [4:0] $end
$var wire 1 4 p43 $end
$var wire 1 5 p32 $end
$var wire 1 6 p31 $end
$var wire 1 7 p22 $end
$var wire 1 8 p11 $end
$var wire 1 9 g43 $end
$var wire 1 : g32 $end
$var wire 1 ; g31 $end
$var wire 1 < g22 $end
$var wire 1 = g11 $end
$var wire 1 " cout_out $end
$var wire 5 > b [4:0] $end
$var wire 5 ? a [4:0] $end
$var wire 1 @ C1 $end
$scope module L1_10 $end
$var wire 1 A g_ji $end
$var wire 1 = g_ki $end
$var wire 1 B g_kj $end
$var wire 1 C p_ji $end
$var wire 1 8 p_ki $end
$var wire 1 D p_kj $end
$upscope $end
$scope module L1_32 $end
$var wire 1 E g_ji $end
$var wire 1 ; g_ki $end
$var wire 1 F g_kj $end
$var wire 1 G p_ji $end
$var wire 1 6 p_ki $end
$var wire 1 H p_kj $end
$upscope $end
$scope module L2_210 $end
$var wire 1 = g_ji $end
$var wire 1 < g_ki $end
$var wire 1 I g_kj $end
$var wire 1 8 p_ji $end
$var wire 1 7 p_ki $end
$var wire 1 J p_kj $end
$upscope $end
$scope module L2_310 $end
$var wire 1 = g_ji $end
$var wire 1 : g_ki $end
$var wire 1 ; g_kj $end
$var wire 1 8 p_ji $end
$var wire 1 5 p_ki $end
$var wire 1 6 p_kj $end
$upscope $end
$scope module L3_40123 $end
$var wire 1 : g_ji $end
$var wire 1 9 g_ki $end
$var wire 1 K g_kj $end
$var wire 1 5 p_ji $end
$var wire 1 4 p_ki $end
$var wire 1 L p_kj $end
$upscope $end
$scope module da0 $end
$var wire 1 ) clk $end
$var wire 1 M d $end
$var reg 1 N q $end
$upscope $end
$scope module da1 $end
$var wire 1 ) clk $end
$var wire 1 O d $end
$var reg 1 P q $end
$upscope $end
$scope module da2 $end
$var wire 1 ) clk $end
$var wire 1 Q d $end
$var reg 1 R q $end
$upscope $end
$scope module da3 $end
$var wire 1 ) clk $end
$var wire 1 S d $end
$var reg 1 T q $end
$upscope $end
$scope module da4 $end
$var wire 1 ) clk $end
$var wire 1 U d $end
$var reg 1 V q $end
$upscope $end
$scope module db0 $end
$var wire 1 ) clk $end
$var wire 1 W d $end
$var reg 1 X q $end
$upscope $end
$scope module db1 $end
$var wire 1 ) clk $end
$var wire 1 Y d $end
$var reg 1 Z q $end
$upscope $end
$scope module db2 $end
$var wire 1 ) clk $end
$var wire 1 [ d $end
$var reg 1 \ q $end
$upscope $end
$scope module db3 $end
$var wire 1 ) clk $end
$var wire 1 ] d $end
$var reg 1 ^ q $end
$upscope $end
$scope module db4 $end
$var wire 1 ) clk $end
$var wire 1 _ d $end
$var reg 1 ` q $end
$upscope $end
$scope module dcout $end
$var wire 1 ) clk $end
$var wire 1 - d $end
$var reg 1 " q $end
$upscope $end
$scope module ds0 $end
$var wire 1 ) clk $end
$var wire 1 a d $end
$var reg 1 b q $end
$upscope $end
$scope module ds1 $end
$var wire 1 ) clk $end
$var wire 1 c d $end
$var reg 1 d q $end
$upscope $end
$scope module ds2 $end
$var wire 1 ) clk $end
$var wire 1 e d $end
$var reg 1 f q $end
$upscope $end
$scope module ds3 $end
$var wire 1 ) clk $end
$var wire 1 g d $end
$var reg 1 h q $end
$upscope $end
$scope module ds4 $end
$var wire 1 ) clk $end
$var wire 1 i d $end
$var reg 1 j q $end
$upscope $end
$upscope $end
$upscope $end
$enddefinitions $end
$comment Show the parameter values. $end
$dumpall
$end
#0
$dumpvars
xj
xi
xh
xg
xf
xe
xd
xc
xb
xa
x`
0_
x^
0]
x\
0[
xZ
1Y
xX
0W
xV
0U
xT
0S
xR
0Q
xP
0O
xN
1M
xL
xK
xJ
xI
xH
xG
xF
xE
xD
xC
xB
xA
x@
bx ?
bx >
x=
x<
x;
x:
x9
x8
x7
x6
x5
x4
bx 3
bx 2
b10 1
b1 0
bx /
bx .
x-
x,
x+
x*
0)
b10 (
bx '
bx &
b1 %
bx $
bx #
x"
bx !
$end
#5000
0i
0e
0g
0,
0:
05
1c
0*
0=
0;
0+
0<
0-
09
18
06
07
04
1a
0B
0A
0F
0E
0I
0K
0@
1D
1C
0H
0G
0J
0L
b11 3
b0 .
b11 /
1N
0P
0R
0T
b1 ?
0V
0X
1Z
0\
0^
b10 >
0`
b10 &
b1 #
1)
#10000
0)
#15000
b10 '
b1 $
0"
0j
0h
0f
1d
b11 !
b11 2
1b
1)
#20000
1W
1Q
0)
b11 (
b11 1
b101 %
b101 0
#25000
1g
1+
1<
1*
1=
0c
0e
08
07
0a
1A
1@
0C
1G
1J
b1000 3
b1 .
b110 /
b101 ?
1R
b11 >
1X
b11 &
b101 #
1)
#30000
0)
#35000
b11 '
b101 $
1h
0d
b1000 !
b1000 2
0b
1)
#40000
0Y
1O
1S
1U
0)
b1 (
b1 1
b11111 %
b11111 0
#45000
1-
19
1,
1:
0g
0i
16
b0 3
1H
1L
b11110 /
1P
1T
b11111 ?
1V
b1 >
0Z
b1 &
b11111 #
1)
#50000
0)
#55000
b1 '
b11111 $
1"
b0 !
b0 2
0h
1)
#60000
0W
1Y
1]
0O
0S
0)
b1010 (
b1010 1
b10101 %
b10101 0
#65000
1g
0-
09
1i
0+
0<
0,
0:
1e
14
0*
0=
1c
17
15
18
1a
0A
0@
1C
b11111 3
b0 .
b11111 /
0P
b10101 ?
0T
0X
1Z
b1010 >
1^
b1010 &
b10101 #
1)
#70000
0)
#75000
b1010 '
b10101 $
0"
1j
1h
1f
1d
b11111 !
b11111 2
1b
1)
#80000
1W
0Y
1[
0]
1O
1S
0U
0)
b101 (
b101 1
b1111 %
b1111 0
#85000
1,
1:
0g
1*
1=
1;
0c
05
1e
1i
1+
1<
08
06
07
04
0a
1A
1E
1I
1@
0C
0G
0J
0L
b10100 3
b101 .
b1010 /
1P
1T
b1111 ?
0V
1X
0Z
1\
b101 >
0^
b101 &
b1111 #
1)
#90000
0)
#95000
b101 '
b1111 $
0h
0d
b10100 !
b10100 2
0b
1)
